[
    {
        "findingDetails": "Using the iam:PassRole action with wildcards (*) in the resource can be overly permissive because it allows iam:PassRole permissions on multiple resources. We recommend that you specify resource ARNs or add the iam:PassedToService condition key to your statement.",
        "findingType": "SECURITY_WARNING",
        "issueCode": "PASS_ROLE_WITH_STAR_IN_RESOURCE",
        "learnMoreLink": "https://docs.aws.amazon.com/IAM/latest/UserGuide/access-analyzer-reference-policy-checks.html#access-analyzer-reference-policy-checks-security-warning-pass-role-with-star-in-resource",
        "locations": [
            {
                "path": [
                    {
                        "value": "Statement"
                    },
                    {
                        "index": 0
                    },
                    {
                        "value": "Action"
                    },
                    {
                        "index": 14
                    }
                ],
                "span": {
                    "end": {
                        "column": 483,
                        "line": 1,
                        "offset": 483
                    },
                    "start": {
                        "column": 469,
                        "line": 1,
                        "offset": 469
                    }
                }
            },
            {
                "path": [
                    {
                        "value": "Statement"
                    },
                    {
                        "index": 0
                    },
                    {
                        "value": "Resource"
                    },
                    {
                        "index": 0
                    }
                ],
                "span": {
                    "end": {
                        "column": 525,
                        "line": 1,
                        "offset": 525
                    },
                    "start": {
                        "column": 522,
                        "line": 1,
                        "offset": 522
                    }
                }
            }
        ]
    }
]